RomKit/__init__.py
RomKit/orgposter/__init__.py
RomKit/orgposter/config.py
RomKit/orgposter/id_tracker.py
RomKit/orgposter/json_reader.py
RomKit/orgposter/main.py
RomKit/orgposter/placeholders.py
RomKit/utils/__init__.py
RomKit/utils/message.py
RomKit/utils/telegram.py
RomKit/utils/version.py
romkit-1.0.1.dist-info/METADATA
romkit-1.0.1.dist-info/WHEEL
romkit-1.0.1.dist-info/licenses/LICENSE
romkit-1.0.1.dist-info/RECORD
