Metadata-Version: 2.4
Name: RomKit
Version: 1.0.1
Summary: Python Library for ROM Project Automation
License: GPL-3.0
License-File: LICENSE
Keywords: rom,android,telegram,automation,ota,github-actions
Author: PrajjuS
Author-email: theprajjus@gmail.com
Requires-Python: >=3.10
Classifier: License :: OSI Approved :: GNU General Public License v3 (GPLv3)
Classifier: Operating System :: OS Independent
Classifier: Programming Language :: Python :: 3
Classifier: Programming Language :: Python :: 3.10
Classifier: Programming Language :: Python :: 3.11
Classifier: Programming Language :: Python :: 3.12
Classifier: Programming Language :: Python :: 3.13
Classifier: Programming Language :: Python :: 3.14
Classifier: Topic :: Communications :: Chat
Classifier: Topic :: Software Development :: Libraries :: Python Modules
Requires-Dist: jinja2 (>=3.1.6,<4.0.0)
Requires-Dist: pygithub (>=2.8.1,<3.0.0)
Requires-Dist: pytelegrambotapi (>=4.29.1,<5.0.0)
Project-URL: Homepage, https://github.com/PrajjuS/RomKit
Project-URL: Repository, https://github.com/PrajjuS/RomKit
